web_extractor/__init__.py
web_extractor/server.py
testpythonmcp-0.1.2.dist-info/METADATA
testpythonmcp-0.1.2.dist-info/WHEEL
testpythonmcp-0.1.2.dist-info/entry_points.txt
testpythonmcp-0.1.2.dist-info/top_level.txt
testpythonmcp-0.1.2.dist-info/RECORD
