Metadata-Version: 2.4
Name: testpythonmcp
Version: 0.1.2
Summary: Add your description here
License: MIT
Requires-Python: >=3.12
Requires-Dist: mcp>=1.2.0
Requires-Dist: requests
Requires-Dist: beautifulsoup4
